python_lic_sys/__init__.py
python_lic_sys/pyli.py
python_lic_sys-0.0.4.dist-info/LICENSE
python_lic_sys-0.0.4.dist-info/METADATA
python_lic_sys-0.0.4.dist-info/WHEEL
python_lic_sys-0.0.4.dist-info/top_level.txt
python_lic_sys-0.0.4.dist-info/RECORD
