Metadata-Version: 2.1
Name: python-lic-sys
Version: 0.0.4
Summary: A Easy Softwear Licensing
Home-page: https://github.com/PythonProgramme/Python-Code
Author: TechSmit
Author-email: techsmitdevloper@gmail.com
License: UNKNOWN
Platform: UNKNOWN
Classifier: Programming Language :: Python :: 3
Classifier: License :: OSI Approved :: MIT License
Classifier: Operating System :: OS Independent
Requires-Python: >=3.6
